Workbook

Sheet 00_Inputs
A1: Input | B1: Value | C1: Notes
A2: Household income (annual) | B2: 150000 | C2: US family of four example
A3: Savings rate | B3: 0.3 | C3: Discipline target
A4: Annual investing | B4: =B2*B3 | C4: Auto-calculated
A5: Current portfolio | B5: 250000 | C5: Starting investments
A6: Annual expenses (FI target) | B6: 90000 | C6: Required annual spend
A7: FI withdrawal rate | B7: 0.04 | C7: Conservative default
A8: FI number | B8: =B6/B7 | C8: Target portfolio
A9: Expected nominal return | B9: 0.075 | C9: Long-run conservative assumption
A10: Inflation | B10: 0.03 | C10: Long-run assumption
A11: Real return | B11: =(1+B9)/(1+B10)-1 | C11: Inflation adjusted
A12: Years modeled | B12: 20 | C12: Planning horizon
A13: Starting withdrawal (annual) | B13: 90000 | C13: Initial retirement draw
A14: Housing: annual ownership cost | B14: 36000 | C14: Mortgage+tax+insurance+maint
A15: Housing: annual rent cost | B15: 30000 | C15: Rent + renter insurance

Sheet 01_Cashflow
A1: Category | B1: Annual | C1: Monthly | D1: Ratio | E1: Notes
A2: Income | B2: ='00_Inputs'!B2 | C2: =B2/12 | D2: 1 | E2: From inputs
A3: Investing | B3: ='00_Inputs'!B4 | C3: =B3/12 | D3: =B3/B2 | E3: Auto transfer
A4: Needs (fixed) | B4: =B2*0.42 | C4: =B4/12 | D4: =B4/B2 | E4: Mortgage, utilities, insurance
A5: Wants (joy) | B5: =B2*0.18 | C5: =B5/12 | D5: =B5/B2 | E5: Travel, dining, experiences
A6: Other | B6: =B2-B3-B4-B5 | C6: =B6/12 | D6: =B6/B2 | E6: Buffer + irregular spend
A7: Savings + investing rate | B7: =B3/B2 | D7: =B3/B2 | E7: Keep at or above 25%

Sheet 02_FI_Tracker
A1: Year | B1: Starting Portfolio | C1: Contribution | D1: Growth | E1: Ending Portfolio | F1: FI Number | G1: FI Progress %
A2: 0 | B2: ='00_Inputs'!B5 | C2: ='00_Inputs'!B4 | D2: 0 | E2: =B2+C2+D2 | F2: ='00_Inputs'!B8 | G2: =E2/F2
A3: =A2+1 | B3: =E2 | C3: ='00_Inputs'!B4 | D3: =B3*'00_Inputs'!B9 | E3: =B3+C3+D3 | F3: ='00_Inputs'!B8 | G3: =E3/F3
A4: =A3+1 | B4: =E3 | C4: ='00_Inputs'!B4 | D4: =B4*'00_Inputs'!B9 | E4: =B4+C4+D4 | F4: ='00_Inputs'!B8 | G4: =E4/F4
A5: =A4+1 | B5: =E4 | C5: ='00_Inputs'!B4 | D5: =B5*'00_Inputs'!B9 | E5: =B5+C5+D5 | F5: ='00_Inputs'!B8 | G5: =E5/F5
A6: =A5+1 | B6: =E5 | C6: ='00_Inputs'!B4 | D6: =B6*'00_Inputs'!B9 | E6: =B6+C6+D6 | F6: ='00_Inputs'!B8 | G6: =E6/F6
A7: =A6+1 | B7: =E6 | C7: ='00_Inputs'!B4 | D7: =B7*'00_Inputs'!B9 | E7: =B7+C7+D7 | F7: ='00_Inputs'!B8 | G7: =E7/F7
A8: =A7+1 | B8: =E7 | C8: ='00_Inputs'!B4 | D8: =B8*'00_Inputs'!B9 | E8: =B8+C8+D8 | F8: ='00_Inputs'!B8 | G8: =E8/F8
A9: =A8+1 | B9: =E8 | C9: ='00_Inputs'!B4 | D9: =B9*'00_Inputs'!B9 | E9: =B9+C9+D9 | F9: ='00_Inputs'!B8 | G9: =E9/F9
A10: =A9+1 | B10: =E9 | C10: ='00_Inputs'!B4 | D10: =B10*'00_Inputs'!B9 | E10: =B10+C10+D10 | F10: ='00_Inputs'!B8 | G10: =E10/F10
A11: =A10+1 | B11: =E10 | C11: ='00_Inputs'!B4 | D11: =B11*'00_Inputs'!B9 | E11: =B11+C11+D11 | F11: ='00_Inputs'!B8 | G11: =E11/F11
A12: =A11+1 | B12: =E11 | C12: ='00_Inputs'!B4 | D12: =B12*'00_Inputs'!B9 | E12: =B12+C12+D12 | F12: ='00_Inputs'!B8 | G12: =E12/F12
A13: =A12+1 | B13: =E12 | C13: ='00_Inputs'!B4 | D13: =B13*'00_Inputs'!B9 | E13: =B13+C13+D13 | F13: ='00_Inputs'!B8 | G13: =E13/F13
A14: =A13+1 | B14: =E13 | C14: ='00_Inputs'!B4 | D14: =B14*'00_Inputs'!B9 | E14: =B14+C14+D14 | F14: ='00_Inputs'!B8 | G14: =E14/F14
A15: =A14+1 | B15: =E14 | C15: ='00_Inputs'!B4 | D15: =B15*'00_Inputs'!B9 | E15: =B15+C15+D15 | F15: ='00_Inputs'!B8 | G15: =E15/F15
A16: =A15+1 | B16: =E15 | C16: ='00_Inputs'!B4 | D16: =B16*'00_Inputs'!B9 | E16: =B16+C16+D16 | F16: ='00_Inputs'!B8 | G16: =E16/F16
A17: =A16+1 | B17: =E16 | C17: ='00_Inputs'!B4 | D17: =B17*'00_Inputs'!B9 | E17: =B17+C17+D17 | F17: ='00_Inputs'!B8 | G17: =E17/F17
A18: =A17+1 | B18: =E17 | C18: ='00_Inputs'!B4 | D18: =B18*'00_Inputs'!B9 | E18: =B18+C18+D18 | F18: ='00_Inputs'!B8 | G18: =E18/F18
A19: =A18+1 | B19: =E18 | C19: ='00_Inputs'!B4 | D19: =B19*'00_Inputs'!B9 | E19: =B19+C19+D19 | F19: ='00_Inputs'!B8 | G19: =E19/F19
A20: =A19+1 | B20: =E19 | C20: ='00_Inputs'!B4 | D20: =B20*'00_Inputs'!B9 | E20: =B20+C20+D20 | F20: ='00_Inputs'!B8 | G20: =E20/F20
A21: =A20+1 | B21: =E20 | C21: ='00_Inputs'!B4 | D21: =B21*'00_Inputs'!B9 | E21: =B21+C21+D21 | F21: ='00_Inputs'!B8 | G21: =E21/F21
A22: =A21+1 | B22: =E21 | C22: ='00_Inputs'!B4 | D22: =B22*'00_Inputs'!B9 | E22: =B22+C22+D22 | F22: ='00_Inputs'!B8 | G22: =E22/F22
A23: =A22+1 | B23: =E22 | C23: ='00_Inputs'!B4 | D23: =B23*'00_Inputs'!B9 | E23: =B23+C23+D23 | F23: ='00_Inputs'!B8 | G23: =E23/F23

Sheet 03_Compound_Path
A1: Year | B1: Starting Corpus | C1: Annual Contribution | D1: Growth | E1: Ending Corpus | F1: Real Corpus
A2: 0 | B2: ='00_Inputs'!B5 | C2: ='00_Inputs'!B4 | D2: 0 | E2: =B2+C2+D2 | F2: =E2
A3: =A2+1 | B3: =E2 | C3: ='00_Inputs'!B4 | D3: =B3*'00_Inputs'!B9 | E3: =B3+C3+D3 | F3: =E3/((1+'00_Inputs'!B10)^A3)
A4: =A3+1 | B4: =E3 | C4: ='00_Inputs'!B4 | D4: =B4*'00_Inputs'!B9 | E4: =B4+C4+D4 | F4: =E4/((1+'00_Inputs'!B10)^A4)
A5: =A4+1 | B5: =E4 | C5: ='00_Inputs'!B4 | D5: =B5*'00_Inputs'!B9 | E5: =B5+C5+D5 | F5: =E5/((1+'00_Inputs'!B10)^A5)
A6: =A5+1 | B6: =E5 | C6: ='00_Inputs'!B4 | D6: =B6*'00_Inputs'!B9 | E6: =B6+C6+D6 | F6: =E6/((1+'00_Inputs'!B10)^A6)
A7: =A6+1 | B7: =E6 | C7: ='00_Inputs'!B4 | D7: =B7*'00_Inputs'!B9 | E7: =B7+C7+D7 | F7: =E7/((1+'00_Inputs'!B10)^A7)
A8: =A7+1 | B8: =E7 | C8: ='00_Inputs'!B4 | D8: =B8*'00_Inputs'!B9 | E8: =B8+C8+D8 | F8: =E8/((1+'00_Inputs'!B10)^A8)
A9: =A8+1 | B9: =E8 | C9: ='00_Inputs'!B4 | D9: =B9*'00_Inputs'!B9 | E9: =B9+C9+D9 | F9: =E9/((1+'00_Inputs'!B10)^A9)
A10: =A9+1 | B10: =E9 | C10: ='00_Inputs'!B4 | D10: =B10*'00_Inputs'!B9 | E10: =B10+C10+D10 | F10: =E10/((1+'00_Inputs'!B10)^A10)
A11: =A10+1 | B11: =E10 | C11: ='00_Inputs'!B4 | D11: =B11*'00_Inputs'!B9 | E11: =B11+C11+D11 | F11: =E11/((1+'00_Inputs'!B10)^A11)
A12: =A11+1 | B12: =E11 | C12: ='00_Inputs'!B4 | D12: =B12*'00_Inputs'!B9 | E12: =B12+C12+D12 | F12: =E12/((1+'00_Inputs'!B10)^A12)
A13: =A12+1 | B13: =E12 | C13: ='00_Inputs'!B4 | D13: =B13*'00_Inputs'!B9 | E13: =B13+C13+D13 | F13: =E13/((1+'00_Inputs'!B10)^A13)
A14: =A13+1 | B14: =E13 | C14: ='00_Inputs'!B4 | D14: =B14*'00_Inputs'!B9 | E14: =B14+C14+D14 | F14: =E14/((1+'00_Inputs'!B10)^A14)
A15: =A14+1 | B15: =E14 | C15: ='00_Inputs'!B4 | D15: =B15*'00_Inputs'!B9 | E15: =B15+C15+D15 | F15: =E15/((1+'00_Inputs'!B10)^A15)
A16: =A15+1 | B16: =E15 | C16: ='00_Inputs'!B4 | D16: =B16*'00_Inputs'!B9 | E16: =B16+C16+D16 | F16: =E16/((1+'00_Inputs'!B10)^A16)
A17: =A16+1 | B17: =E16 | C17: ='00_Inputs'!B4 | D17: =B17*'00_Inputs'!B9 | E17: =B17+C17+D17 | F17: =E17/((1+'00_Inputs'!B10)^A17)
A18: =A17+1 | B18: =E17 | C18: ='00_Inputs'!B4 | D18: =B18*'00_Inputs'!B9 | E18: =B18+C18+D18 | F18: =E18/((1+'00_Inputs'!B10)^A18)
A19: =A18+1 | B19: =E18 | C19: ='00_Inputs'!B4 | D19: =B19*'00_Inputs'!B9 | E19: =B19+C19+D19 | F19: =E19/((1+'00_Inputs'!B10)^A19)
A20: =A19+1 | B20: =E19 | C20: ='00_Inputs'!B4 | D20: =B20*'00_Inputs'!B9 | E20: =B20+C20+D20 | F20: =E20/((1+'00_Inputs'!B10)^A20)
A21: =A20+1 | B21: =E20 | C21: ='00_Inputs'!B4 | D21: =B21*'00_Inputs'!B9 | E21: =B21+C21+D21 | F21: =E21/((1+'00_Inputs'!B10)^A21)
A22: =A21+1 | B22: =E21 | C22: ='00_Inputs'!B4 | D22: =B22*'00_Inputs'!B9 | E22: =B22+C22+D22 | F22: =E22/((1+'00_Inputs'!B10)^A22)
A23: =A22+1 | B23: =E22 | C23: ='00_Inputs'!B4 | D23: =B23*'00_Inputs'!B9 | E23: =B23+C23+D23 | F23: =E23/((1+'00_Inputs'!B10)^A23)

Sheet 04_Withdrawal
A1: Year | B1: Starting Portfolio | C1: Withdrawal | D1: Growth | E1: Ending Portfolio | F1: Sustainable?
A2: 0 | B2: ='02_FI_Tracker'!E23 | C2: ='00_Inputs'!B13 | D2: 0 | E2: =B2-C2+D2 | F2: =IF(E2>0,"Yes","No")
A3: =A2+1 | B3: =E2 | C3: =C2*(1+'00_Inputs'!B10) | D3: =B3*'00_Inputs'!B9 | E3: =B3-C3+D3 | F3: =IF(E3>0,"Yes","No")
A4: =A3+1 | B4: =E3 | C4: =C3*(1+'00_Inputs'!B10) | D4: =B4*'00_Inputs'!B9 | E4: =B4-C4+D4 | F4: =IF(E4>0,"Yes","No")
A5: =A4+1 | B5: =E4 | C5: =C4*(1+'00_Inputs'!B10) | D5: =B5*'00_Inputs'!B9 | E5: =B5-C5+D5 | F5: =IF(E5>0,"Yes","No")
A6: =A5+1 | B6: =E5 | C6: =C5*(1+'00_Inputs'!B10) | D6: =B6*'00_Inputs'!B9 | E6: =B6-C6+D6 | F6: =IF(E6>0,"Yes","No")
A7: =A6+1 | B7: =E6 | C7: =C6*(1+'00_Inputs'!B10) | D7: =B7*'00_Inputs'!B9 | E7: =B7-C7+D7 | F7: =IF(E7>0,"Yes","No")
A8: =A7+1 | B8: =E7 | C8: =C7*(1+'00_Inputs'!B10) | D8: =B8*'00_Inputs'!B9 | E8: =B8-C8+D8 | F8: =IF(E8>0,"Yes","No")
A9: =A8+1 | B9: =E8 | C9: =C8*(1+'00_Inputs'!B10) | D9: =B9*'00_Inputs'!B9 | E9: =B9-C9+D9 | F9: =IF(E9>0,"Yes","No")
A10: =A9+1 | B10: =E9 | C10: =C9*(1+'00_Inputs'!B10) | D10: =B10*'00_Inputs'!B9 | E10: =B10-C10+D10 | F10: =IF(E10>0,"Yes","No")
A11: =A10+1 | B11: =E10 | C11: =C10*(1+'00_Inputs'!B10) | D11: =B11*'00_Inputs'!B9 | E11: =B11-C11+D11 | F11: =IF(E11>0,"Yes","No")
A12: =A11+1 | B12: =E11 | C12: =C11*(1+'00_Inputs'!B10) | D12: =B12*'00_Inputs'!B9 | E12: =B12-C12+D12 | F12: =IF(E12>0,"Yes","No")
A13: =A12+1 | B13: =E12 | C13: =C12*(1+'00_Inputs'!B10) | D13: =B13*'00_Inputs'!B9 | E13: =B13-C13+D13 | F13: =IF(E13>0,"Yes","No")
A14: =A13+1 | B14: =E13 | C14: =C13*(1+'00_Inputs'!B10) | D14: =B14*'00_Inputs'!B9 | E14: =B14-C14+D14 | F14: =IF(E14>0,"Yes","No")
A15: =A14+1 | B15: =E14 | C15: =C14*(1+'00_Inputs'!B10) | D15: =B15*'00_Inputs'!B9 | E15: =B15-C15+D15 | F15: =IF(E15>0,"Yes","No")
A16: =A15+1 | B16: =E15 | C16: =C15*(1+'00_Inputs'!B10) | D16: =B16*'00_Inputs'!B9 | E16: =B16-C16+D16 | F16: =IF(E16>0,"Yes","No")
A17: =A16+1 | B17: =E16 | C17: =C16*(1+'00_Inputs'!B10) | D17: =B17*'00_Inputs'!B9 | E17: =B17-C17+D17 | F17: =IF(E17>0,"Yes","No")
A18: =A17+1 | B18: =E17 | C18: =C17*(1+'00_Inputs'!B10) | D18: =B18*'00_Inputs'!B9 | E18: =B18-C18+D18 | F18: =IF(E18>0,"Yes","No")
A19: =A18+1 | B19: =E18 | C19: =C18*(1+'00_Inputs'!B10) | D19: =B19*'00_Inputs'!B9 | E19: =B19-C19+D19 | F19: =IF(E19>0,"Yes","No")
A20: =A19+1 | B20: =E19 | C20: =C19*(1+'00_Inputs'!B10) | D20: =B20*'00_Inputs'!B9 | E20: =B20-C20+D20 | F20: =IF(E20>0,"Yes","No")
A21: =A20+1 | B21: =E20 | C21: =C20*(1+'00_Inputs'!B10) | D21: =B21*'00_Inputs'!B9 | E21: =B21-C21+D21 | F21: =IF(E21>0,"Yes","No")
A22: =A21+1 | B22: =E21 | C22: =C21*(1+'00_Inputs'!B10) | D22: =B22*'00_Inputs'!B9 | E22: =B22-C22+D22 | F22: =IF(E22>0,"Yes","No")
A23: =A22+1 | B23: =E22 | C23: =C22*(1+'00_Inputs'!B10) | D23: =B23*'00_Inputs'!B9 | E23: =B23-C23+D23 | F23: =IF(E23>0,"Yes","No")
A24: =A23+1 | B24: =E23 | C24: =C23*(1+'00_Inputs'!B10) | D24: =B24*'00_Inputs'!B9 | E24: =B24-C24+D24 | F24: =IF(E24>0,"Yes","No")
A25: =A24+1 | B25: =E24 | C25: =C24*(1+'00_Inputs'!B10) | D25: =B25*'00_Inputs'!B9 | E25: =B25-C25+D25 | F25: =IF(E25>0,"Yes","No")
A26: =A25+1 | B26: =E25 | C26: =C25*(1+'00_Inputs'!B10) | D26: =B26*'00_Inputs'!B9 | E26: =B26-C26+D26 | F26: =IF(E26>0,"Yes","No")
A27: =A26+1 | B27: =E26 | C27: =C26*(1+'00_Inputs'!B10) | D27: =B27*'00_Inputs'!B9 | E27: =B27-C27+D27 | F27: =IF(E27>0,"Yes","No")
A28: =A27+1 | B28: =E27 | C28: =C27*(1+'00_Inputs'!B10) | D28: =B28*'00_Inputs'!B9 | E28: =B28-C28+D28 | F28: =IF(E28>0,"Yes","No")
A29: =A28+1 | B29: =E28 | C29: =C28*(1+'00_Inputs'!B10) | D29: =B29*'00_Inputs'!B9 | E29: =B29-C29+D29 | F29: =IF(E29>0,"Yes","No")
A30: =A29+1 | B30: =E29 | C30: =C29*(1+'00_Inputs'!B10) | D30: =B30*'00_Inputs'!B9 | E30: =B30-C30+D30 | F30: =IF(E30>0,"Yes","No")
A31: =A30+1 | B31: =E30 | C31: =C30*(1+'00_Inputs'!B10) | D31: =B31*'00_Inputs'!B9 | E31: =B31-C31+D31 | F31: =IF(E31>0,"Yes","No")
A32: =A31+1 | B32: =E31 | C32: =C31*(1+'00_Inputs'!B10) | D32: =B32*'00_Inputs'!B9 | E32: =B32-C32+D32 | F32: =IF(E32>0,"Yes","No")
A33: =A32+1 | B33: =E32 | C33: =C32*(1+'00_Inputs'!B10) | D33: =B33*'00_Inputs'!B9 | E33: =B33-C33+D33 | F33: =IF(E33>0,"Yes","No")

Sheet 05_Allocation
A1: Bucket | B1: Target % | C1: Current % | D1: Drift % | E1: Action
A2: US Total Stock | B2: 0.55 | C2: 0.58 | D2: =C2-B2 | E2: =IF(ABS(D2)>0.03,"Rebalance","Hold")
A3: US Total Bond | B3: 0.25 | C3: 0.22 | D3: =C3-B3 | E3: =IF(ABS(D3)>0.03,"Rebalance","Hold")
A4: International Stock | B4: 0.2 | C4: 0.2 | D4: =C4-B4 | E4: =IF(ABS(D4)>0.03,"Rebalance","Hold")
A5: Portfolio Value | B5: ='02_FI_Tracker'!E23 | E5: Auto-linked from FI tracker

Sheet 06_Housing_Model
A1: Metric | B1: Own | C1: Rent | D1: Difference
A2: Annual housing cost | B2: ='00_Inputs'!B14 | C2: ='00_Inputs'!B15 | D2: =B2-C2
A3: 10-year nominal cost | B3: =B2*10 | C3: =C2*10 | D3: =B3-C3
A4: 10-year invested difference | B4: =0 | C4: =D2*(((1+'00_Inputs'!B9)^10-1)/'00_Inputs'!B9) | D4: =C4-B4

Sheet 07_Quarterly_Review
A1: Quarter | B1: Savings Rate | C1: Policy Compliance | D1: Net Worth Growth | E1: Review Score | F1: Action
A2: Q1 | B2: 0.3 | C2: 0.85 | D2: 0.1 | E2: =AVERAGE(B2:D2) | F2: One improvement action for next quarter
A3: Q2 | B3: 0.3 | C3: 0.85 | D3: 0.1 | E3: =AVERAGE(B3:D3) | F3: One improvement action for next quarter
A4: Q3 | B4: 0.3 | C4: 0.85 | D4: 0.1 | E4: =AVERAGE(B4:D4) | F4: One improvement action for next quarter
A5: Q4 | B5: 0.3 | C5: 0.85 | D5: 0.1 | E5: =AVERAGE(B5:D5) | F5: One improvement action for next quarter

Sheet 08_Dashboard
A1: Key Metric | B1: Value | C1: Source
A2: FI Number | B2: ='00_Inputs'!B8 | C2: Inputs
A3: Current Portfolio (Year 20) | B3: ='02_FI_Tracker'!E23 | C3: FI Tracker
A4: FI Progress | B4: ='02_FI_Tracker'!G23 | C4: FI Tracker
A5: Real Portfolio (Year 20) | B5: ='03_Compound_Path'!F23 | C5: Compound Path
A6: Withdrawal Sustainable at Year 30 | B6: ='04_Withdrawal'!F33 | C6: Withdrawal
A7: Allocation Rebalances Needed | B7: =COUNTIF('05_Allocation'!E2:E4,"Rebalance") | C7: Allocation
A8: Quarterly Review Average | B8: =AVERAGE('07_Quarterly_Review'!E2:E5) | C8: Quarterly Review

Sheet 09_Wealth_Priority_Outcomes
A1: Quarter | B1: Focus | C1: Teaching Order | D1: Primary Outcome | E1: Kit Bundle | F1: Action To Take
A2: Q1 | B2: Foundation and downside protection | C2: 1) Protection buffer 2) Employer benefits 3) High-interest debt 4) Emergency runway | D2: Vision, cashflow, and risk systems are active and documented. | E2: Vision Alignment Kit • Cashflow Autopilot Kit • Emergency and Risk Checklist | F2: Lock transfers, finalize family rules, and close safety gaps.
A3: Q2 | B3: Tax-efficient compounding system | C3: 1) Tax-efficient bucket order 2) Max retirement contributions 3) Protect 25%+ savings rate | D3: Tax drag is reduced and policy-based investing is running. | E3: Tax Efficiency Planner • Index Policy Builder • Global Allocation Planner | F3: Set annual contribution plan and rebalance rules.
A4: Q3 | B4: Decision modeling and resilience | C4: 1) Pre-fund major goals 2) Run key decision models | D4: Withdrawal guardrails and major-decision models are in place. | E4: Withdrawal Guardrails Model • Buy vs Rent Model • Education Funding Planner | F4: Model upcoming decisions before committing.
A5: Q4 | B5: Optionality and long-range execution | C5: 1) Build optional corpus 2) Selective debt reduction 3) Quarterly review reset | D5: Behavior systems are stable and the next-year roadmap is clear. | E5: Behavior Discipline System • Work Optional Design Canvas • Annual Review and Decade Plan | F5: Publish the next-year plan and review calendar.

Sheet 10_Wealth_Priority_Order
A1: Step | B1: US Priority | C1: US Action | D1: India Priority | E1: India Action | F1: Priority Quarter | G1: Kit Tie-In
A2: 1 | B2: Cover highest deductible and core protection | C2: Keep deductible cash and verify health, life, and disability coverage. | D2: Set aside deductible + protection buffer | E2: Keep deductible cash and verify health cover, top-up, and term insurance. | F2: Q1 | G2: Q1 Emergency and Risk Checklist
A3: 2 | B3: Capture full employer match | C3: Contribute enough to secure all available 401(k)/403(b)/TSP match dollars. | D3: Capture employer retirement benefits | E3: Secure EPF and employer retirement benefits where applicable. | F3: Q1 | G3: Q1 Cashflow Autopilot + Q2 Tax Efficiency
A4: 3 | B4: Eliminate high-interest debt | C4: Prioritize credit card and high-APR balances before discretionary investing. | D4: Clear high-interest debt first | E4: Prioritize credit card and personal-loan liabilities. | F4: Q1 | G4: Q1 Cashflow Autopilot
A5: 4 | B5: Build emergency reserves | C5: Target 3-6 months of essentials (6-12 months if income is variable). | D5: Build emergency fund runway | E5: Target 6-12 months of essential expenses. | F5: Q1 | G5: Q1 Emergency and Risk Checklist
A6: 5 | B6: Fill tax-advantaged buckets first | C6: Prioritize Roth IRA, HSA, and eligible backdoor paths before taxable investing. | D6: Use tax-efficient buckets in order | E6: Prioritize EPF/VPF, PPF, NPS, and ELSS before taxable investing. | F6: Q2 | G6: Q2 Tax Efficiency Planner
A7: 6 | B7: Max retirement account contributions | C7: Increase payroll contributions toward annual retirement limits. | D7: Max retirement contributions | E7: Raise automated retirement contributions across core buckets. | F7: Q2 | G7: Q2 Tax Efficiency + Q2 Index Policy
A8: 7 | B8: Reach 25%+ gross savings and investing | C8: Automate contributions before lifestyle spending. | D8: Protect 25%+ savings and investing rate | E8: Automate first and control fixed-cost creep. | F8: Q2 | G8: Q1 Cashflow + Q2 Index Policy
A9: 8 | B9: Pre-fund major near-term goals | C9: Create buckets for down payment, kids, and planned transitions. | D9: Pre-fund major goals | E9: Create buckets for home down payment, child education, and family goals. | F9: Q3 | G9: Q3 Buy vs Rent + Q3 Education Funding
A10: 9 | B10: Build flexible taxable wealth + optional debt paydown | C10: Direct surplus to low-cost index investing and selective low-rate debt reduction. | D10: Build optional corpus + selective debt reduction | E10: Direct surplus to diversified index/debt funds and strategic home-loan prepayment. | F10: Q4 | G10: Q3 Withdrawal Guardrails + Q4 Annual Review
